{
  "policies": {
    "Bookmarks": [
      {
        "Placement": "toolbar",
        "Title": "AOS",
        "URL": "http://nimbusserver.aos.com:8000/#/"
      },
      {
        "Placement": "toolbar",
        "Title": "Jenkins",
        "URL": "http://nimbusserver:8090"
      },
      {
        "Placement": "toolbar",
        "Title": "Octane",
        "URL": "http://nimbusserver.aos.com:8085/ui"
      },
      {
        "Placement": "toolbar",
        "Title": "Docker Hub",
        "URL": "https://hub.docker.com"
      },
      {
        "Placement": "toolbar",
        "Title": "JIRA",
        "URL": "http://nimbusserver.aos.com:8099"
      },
      {
        "URL" : "http://nimbusserver.aos.com:8082/qcbin",
        "Folder" : "ADM Products",
        "Placement" : "toolbar",
        "Title" : "ALM"
      },
      {
        "Title" : "Atlas",
        "Placement" : "toolbar",
        "Folder" : "ADM Products",
        "URL" : "http://nimbuswindows:8181/atlas/index.html"
      },
      {
        "Folder" : "ADM Products",
        "Placement" : "toolbar",
        "Title" : "AutoPass",
        "URL" : "https://nimbusserver.aos.com:5814/autopass"
      },
      {
        "URL" : "http://nimbusserver:8089/da",
        "Folder" : "ADM Products",
        "Placement" : "toolbar",
        "Title" : "Deployment Automation (DA)"
      },
      {
        "Folder" : "ADM Products",
        "Title" : "Fortify Software Security Center (SSC)",
        "Placement" : "toolbar",
        "URL" : "http://nimbusserver:8086/ssc/#/"
      },
      {
        "Placement" : "toolbar",
        "Title" : "Jira",
        "Folder" : "ADM Products",
        "URL" : "http://nimbusserver.aos.com:8099/"
      },
      {
        "URL" : "http://nimbuswindows:8181/ConnectWeb/",
        "Title" : "MF Connect",
        "Placement" : "toolbar",
        "Folder" : "ADM Products"
      },
      {
        "URL" : "http://nimbusserver.aos.com:8084/integration/#/login",
        "Placement" : "toolbar",
        "Title" : "Mobile Center (MC)",
        "Folder" : "ADM Products"
      },
      {
        "URL" : "http://nimbusclient:8182/shunra/auth/login",
        "Title" : "Network Virtualization (NV)",
        "Placement" : "toolbar",
        "Folder" : "ADM Products"
      },
      {
        "URL" : "http://nimbusserver.aos.com:8087/",
        "Folder" : "PPM",
        "Title" : "Project and Portolio Management (PPM)",
        "Placement" : "toolbar"
      },
      {
        "URL" : "http://nimbusserver.aos.com:8088/",
        "Folder" : "PPM",
        "Placement" : "toolbar",
        "Title" : "PPM Launch Pages"
      },
      {
        "Folder" : "ADM Products",
        "Title" : "Rhythm",
        "Placement" : "toolbar",
        "URL" : "http://nimbuswindows:8181/atlas/#perspective=agile"
      },
      {
        "URL" : "http://nimbuswindows/workcenter/tmtrack.dll?StdPage&Template=rlc/admin&/administration/plugins",
        "Folder" : "ADM Products",
        "Title" : "RLC Admin",
        "Placement" : "toolbar"
      },
      {
        "Title" : "SaaS Login",
        "Placement" : "toolbar",
        "Folder" : "ADM Products",
        "URL" : "https://home.software.microfocus.com/myaccount/"
      },
      {
        "Placement" : "toolbar",
        "Title" : "SBM User Workspace",
        "Folder" : "SBM",
        "URL" : "http://nimbuswindows/tmtrack/tmtrack.dll"
      },
      {
        "Placement" : "toolbar",
        "Title" : "SBM Workcenter",
        "Folder" : "SBM",
        "URL" : "http://nimbuswindows/workcenter"
      },
      {
        "URL" : "http://nimbuswindows:8085/mashupmgr",
        "Folder" : "SBM",
        "Title" : "MashUp Mgr",
        "Placement" : "toolbar"
      },
      {
        "URL" : "http://nimbuswindows:19120/login",
        "Folder" : "ADM Products",
        "Placement" : "toolbar",
        "Title" : "Silk Central (SC)"
      },
      {
        "Folder" : "SV",
        "Title" : "SV Lab Server",
        "Placement" : "toolbar",
        "URL" : "https://nimbusserver:8445/api"
      },
      {
        "URL" : "https://nimbusserver:6086/management",
        "Placement" : "toolbar",
        "Title" : "SV Management",
        "Folder" : "SV"
      },
      {
        "Title" : "SV Server",
        "Placement" : "toolbar",
        "Folder" : "SV",
        "URL" : "https://nimbusserver:6085/management"
      }
    ],
    "NoDefaultBookmarks": true,
    "DisplayBookmarksToolbar": true,
    "Extensions": {
      "Install": [
        "//usr/lib64/firefox/distribution/extensions/FT.FirefoxAgent@microfocus.com.xpi"
      ]
    }
  }
}
